{"chunk_definitions":[{"row":190,"row_count":1,"visible":true,"expansion_state":0,"options":{"engine":"r","label":"unnamed-chunk-13"},"document_id":"55900E63","chunk_id":"c7hba5ry2c7ce","chunk_label":"unnamed-chunk-6"},{"row":231,"row_count":1,"visible":true,"expansion_state":0,"options":{"engine":"r","label":"unnamed-chunk-48"},"document_id":"55900E63","chunk_id":"c55r5pdpkx643","chunk_label":"unnamed-chunk-7"},{"row":246,"row_count":1,"visible":true,"expansion_state":0,"options":{"engine":"r","warning":false,"label":"unnamed-chunk-45"},"document_id":"55900E63","chunk_id":"c8yyqd9oqbhz2","chunk_label":"unnamed-chunk-8"}],"doc_write_time":1668955539,"chunk_rendered_width":700}